imppkg/__init__.py
imppkg/data.json
imppkg/harmonic_mean.c
imppkg/harmonic_mean.cpython-310-darwin.so
imppkg/harmonic_mean.pyi
imppkg/harmonic_mean.pyx
imppkg/harmony.py
imppkg/hello.py
imppkg/py.typed
pubpypack_harmony_sourcedelica-0.0.6.dist-info/METADATA
pubpypack_harmony_sourcedelica-0.0.6.dist-info/WHEEL
pubpypack_harmony_sourcedelica-0.0.6.dist-info/entry_points.txt
pubpypack_harmony_sourcedelica-0.0.6.dist-info/top_level.txt
pubpypack_harmony_sourcedelica-0.0.6.dist-info/RECORD
