Metadata-Version: 2.1
Name: pubpypack-harmony-sourcedelica
Version: 0.0.6
Summary: This package does harmonious things
License: UNKNOWN
Platform: UNKNOWN
Requires-Dist: termcolor (<2,>=1.1.0)
